sputils/__init__.py
sputils/__main__.py
sputils/sputils.py
spotify_sputils-0.2.0.dist-info/AUTHORS.rst
spotify_sputils-0.2.0.dist-info/LICENSE
spotify_sputils-0.2.0.dist-info/METADATA
spotify_sputils-0.2.0.dist-info/WHEEL
spotify_sputils-0.2.0.dist-info/dependency_links.txt
spotify_sputils-0.2.0.dist-info/entry_points.txt
spotify_sputils-0.2.0.dist-info/top_level.txt
spotify_sputils-0.2.0.dist-info/RECORD
