Metadata-Version: 2.1
Name: spotify-sputils
Version: 0.2.0
Summary: A collection of spotify utilities, designed to be used in conjunction with other shell utilities.
Home-page: https://github.com/shanedabes/sputils
Author: Shane Donohoe
Author-email: shane@donohoe.cc
License: Apache Software License 2.0
Keywords: sputils
Platform: UNKNOWN
Classifier: Intended Audience :: Developers
Classifier: License :: OSI Approved :: Apache Software License
Classifier: Natural Language :: English
Classifier: Programming Language :: Python :: 3
Classifier: Programming Language :: Python :: 3.6
Classifier: Programming Language :: Python :: 3.7
Requires-Dist: ConfigArgParse (==0.14.0)
Requires-Dist: PyYAML (==5.1)
Requires-Dist: spotipy (==2.4.4)
